{"meta": {"breadcrumbs": {"/": "Главная", "/catalog/elektronika": "Электроника"}, "category_name": "Сетевое оборудование", "product_number": 6102}, "products": {"/catalog/151960867/detail.aspx": {"name": "JIO  / Беспроводной мобильный роутер Wi-Fi модем 4G карманный", "price": 2198, "discount": 4996, "rating": 4, "count": 13, "index": 0}, "/catalog/65064516/detail.aspx": {"name": "РЭМО  / Усилитель интернет-сигнала BAS2341 Turbo", "price": 2590, "discount": 2590, "rating": 5, "count": 89, "index": 1}, "/catalog/130209761/detail.aspx": {"name": "ALFATREND  / Усилитель сигнала сотовой связи мобильного интернета", "price": 9000, "discount": 18000, "rating": 5, "count": 465, "index": 2}, "/catalog/146426680/detail.aspx": {"name": "Gold Master  / Беспроводной Wi-Fi роутер GM 4G SUPER MICRO", "price": 3920, "discount": 8000, "rating": "", "count": 0, "index": 3}, "/catalog/91173399/detail.aspx": {"name": "Wingstel  / Усилитель мобильного сигнала интернета репитер 2G 3G 4G", "price": 7777, "discount": 15554, "rating": 5, "count": 303, "index": 4}, "/catalog/150126980/detail.aspx": {"name": "DF HAO  / Роутер wi fi 4g с поддержкой сим карты 4 антенны", "price": 3520, "discount": 11000, "rating": 5, "count": 70, "index": 5}, "/catalog/142821579/detail.aspx": {"name": "Netis  / Беспроводной Wi-Fi роутер W1", "price": 1200, "discount": 4000, "rating": 5, "count": 2, "index": 6}, "/catalog/120349481/detail.aspx": {"name": "Усилитель сотового связи 3G 4G LTE Репитер  / Усилитель интернет-сигнала", "price": 6956, "discount": 18800, "rating": 4, "count": 99, "index": 7}, "/catalog/65907434/detail.aspx": {"name": "TP-Link  / Роутеры Archer C80", "price": 3729, "discount": 3729, "rating": 5, "count": 304, "index": 8}, "/catalog/116667912/detail.aspx": {"name": "Xiaomi  / Роутер 4A Gigabit маршрутизатор", "price": 2708, "discount": 4837, "rating": 5, "count": 111, "index": 9}, "/catalog/146707430/detail.aspx": {"name": "MobileBonus  / Роутер wi-fi с сим картой 4G", "price": 3914, "discount": 5290, "rating": 5, "count": 61, "index": 10}, "/catalog/144875769/detail.aspx": {"name": "SAGE by Encome  / Усилитель мобильного сигнала и интернета Power Signal", "price": 7286, "discount": 33120, "rating": 5, "count": 46, "index": 11}, "/catalog/82663488/detail.aspx": {"name": "Усилитель сигнала интернета и сотовой связи  / Комплект усиления связи и интернета 2G,3G,4G", "price": 10750, "discount": 21500, "rating": 5, "count": 65, "index": 12}, "/catalog/152263294/detail.aspx": {"name": "Wi-Fi роутер 4g  / Беспроводной с поддержкой сим-карт. Модем", "price": 3375, "discount": 16875, "rating": 5, "count": 34, "index": 13}, "/catalog/141381605/detail.aspx": {"name": "KEENETIC  / Wi-Fi маршрутизатор 100M 4P VIVA KN-1912", "price": 6489, "discount": 9271, "rating": 5, "count": 24, "index": 14}, "/catalog/144850031/detail.aspx": {"name": "Volken  / Усилитель сотовой связи и интернета", "price": 7478, "discount": 32517, "rating": 4, "count": 9, "index": 15}, "/catalog/118170574/detail.aspx": {"name": "Xiaomi  / Wi-Fi Router AC1200 EU", "price": 2871, "discount": 3190, "rating": 5, "count": 43, "index": 16}, "/catalog/153101489/detail.aspx": {"name": "SmartShop  / Wi Fi адаптер с антенной для ПК USB", "price": 400, "discount": 800, "rating": 4, "count": 9, "index": 17}, "/catalog/106255614/detail.aspx": {"name": "Xiaomi  / роутер модем wi-fi, сетевое оборудование tp-link", "price": 2938, "discount": 4740, "rating": 4, "count": 214, "index": 18}, "/catalog/101732328/detail.aspx": {"name": "SmartGadget  / Роутер wi-fi с сим картой 4g", "price": 3995, "discount": 8500, "rating": 4, "count": 122, "index": 19}}}