{"name": "Astial Astial Фрезы для маникюра и педикюра Пуля набор для кутикулы", "rating": 5, "review_count": 66, "article": 71404524, "order_count": 300, "price": 258, "old_price": 892, "detail": "  О товаре      Описание        Фреза с большой рабочей поверхностью хорошо полирует кожу и делает ее глянцевой. Ей удобно шлифовать кутикулу после среза, фреза уберет все недостатки. Фреза пуля на отлично справляется с зачисткой боковых пазух. Очень удобна для обработки пяток в педикюре. Благодаря закругленному кончику уменьшает риск пропилов, поэтому это безопасная фреза. Она подойдет как для начинающих мастеров, так и для профессионалов.\n    Назначение фрезы цилиндрической со скругленным кончиком: шлифовка бокового валика, обработка подошвенной части стопы, обработка трещин, поднятие кутикулы. \n    Фрезы формы закругленный цилиндр не дают вибраций в работе, не ржавеют после дезинфекции и стерилизации, благодаря правильной балансировке Вам будет удобно работать. \n    Зеленая фреза подходит для обработки стоп при гиперкератозе, стержневых мозолях и сухих трещинах. Используется для удаления и зачистки огрубевшей кожи. Применяется в салоне красоты для безопасной очистки и выпиливания старых натоптышей, обработки и выравнивания рельефа кожи. \n    Фрезы с зеленой насечкой имеют увеличенный срок службы за счет поверхностной прочности и твердости рабочей части, поэтому они идеально подходят для подологов. Алмазная фреза (бор стоматологический) Пуля (цилиндр) в ассортименте для маникюра ногтей и кутикулы, зернистость: средняя (с синей насечкой), мягкая (с красной насечкой), грубая (с зеленой насечкой). \n    Эффективность работы фрезы зависит от техники мастера и индивидуальных особенностей кожи и ногтей, поэтому важно подобрать подходящую абразивность! \n    Красная насечка — это тонкая абразивность, фрезы имеют мелкое напыление, они созданы как шлифовщик кожи после применения остальных фрез или деликатной обработки нежной кожи, тонкой кутикулы. \n    Синяя насечка — это среднее алмазное напыление, подходит для работы с нормальной или слегка сухой кожей, поэтому является самым универсальным выбором. \n    Зеленая насечка — это жесткий абразив, алмазное зерно имеет увеличенный размер, применяется для удаления и зачистки огрубевшей кожи, сильно нарастающей кутикулы, ороговелостей, натоптышей. \n    Рекомендуем включить в Ваш набор профессиональные фрезы насадки для маникюрной машинки (аппарата для маникюра). \n    Фрезы алмазные из этого аппаратного маникюрного набора производятся по нашему заказу и под нашим контролем качества на заводе Владмива (Белгород) из нержавеющей стали и имеют алмазное напыление, выполненное гальваническим методом. Фриза отличный полировщик. Такой набор насадок подойдет для срезания кутикулы, выравнивания поверхности, для педикюрного аппарата. Благодаря высоким стандартам качества, фрезы нашей марки Astial обладают повышенной прочностью, остротой и долговечностью. Аппаратный маникюр такими фрезами всегда получается аккуратным и чистым! \n    Российский сертификат соответствия подтверждает высокое качество и позволяет использовать их даже для стоматологии, поэтому их второе название - стоматологические фрезы.\n    За счет универсального хвостовика 2.35 мм такой набор фрез подойдет к профессиональным маникюрным аппаратам, таким как апарат для маникюра Strong (Cтронг), Marathon (Маратон), машинка для маникюра Nail drill, аппарат Nail master, аппарат для маникура и педикюра Keris, Irisk, фрезер для маникюра и педикюра Gulicristal, Inail, Lina и др. \n    Российское производство и наличие регистрационного удостоверения металлической борфрезы гарантируют профессиональному мастеру маникюра в салоне красоты, студии маникюра, а также начинающему дома полное соответствие стандартам качества. Служат гораздо дольше китайских аналогов. \n    С насадками маникюрными и педикюрными Astial можно решить любые задачи мастеров ногтевого сервиса по уходу за ногтями и кутикулой в части шлифовки или полировки, обработки валиков и кутикул, ремонта ногтевой пластины, а также придания нужной формы ногтю, обработки стоп и пяток в педикюре, удаления натоптышей, стержневых мозолей.\n   Инструмент для профессионального и домашнего использования. Подарок мастеру! В нашем магазине вы найдете все для маникюра и все для педикюра, а также другие товары для красоты и здоровья. \n\n\n\nРазвернуть описание\n\n  Описания пока нет. Возможно, оно появится тут позже   Состав  \n\n         Дополнительная информация Страна производства Россия Размер фрез для маникюра 15 мм; крупные; средние Диаметр рабочей части 3.1 мм; 031; 3,1 мм Назначение фрез для маникюра для полировки и шлифовки; обработка кожи и боковых валиков Жесткость фрез для маникюра Средняя (Синяя); средняя Степень обработки Средняя зернистость; крупная; средняя Материал насадки Абразив; алмаз; Нержавеющая сталь Форма фрез для маникюра пуля; фреза для педикюра стопы Длина упаковки 1 см Высота упаковки 7 см Ширина упаковки 9 см Комплектация Алмазная фреза для маникюра - 3 шт; 806.104.274.524.031 (866.104.272.150.031); 806.104.274.514.031 (856.104.272.150.031)  Материалы Материал изделия Нержаввеющая сталь  Общие характеристики Модель Фрезы для педикюра стопы для пяток; цилиндр; Безопасная фреза для маникюра и педикюра  \n\n\n\n\n\nРазвернуть характеристики\n\n    У товара пока нет характеристик. Возможно, они появятся тут позже    Качество подтверждено   Качество подтверждено            Вся информация основывается на последних сведениях от производителя         Сообщить о неточности    ", "category_name": "Косметические аппараты"}