{"name": "BIO CLINIC BIO CLINIC Шампунь для волос профессиональный бессульфатный увлажняющий", "rating": 5, "review_count": 51, "article": 141652376, "order_count": 60, "price": 660, "old_price": 3000, "detail": "  О товаре      Описание    О шикарных волосах, как в рекламе, мечтают и женщины, и мужчины. Но жизнь - не рекламный ролик. Очень часто волосы становятся ломкими и тусклыми. Современная beauty - индустрия предлагает множество профессиональных салонных процедур по восстановлению волос. Но домашний повседневный уход имеет не менее важное значение. Чтобы вернуть волосам жизненную силу и красоту, необходимо подобрать хорошее средство для комплексного ухода и глубокой очистки. Bio Clinic Argan Ultra Care - шампунь для укрепления ослабленных и истонченных женских и мужских волос. Основной компонент его состава - аргановое масло. В комплексе с другими увлажняющими ингредиентами оказывает интенсивный восстанавливающий эффект, питая волосы от корней до самых кончиков, обеспечивая блеск и сияние. Превосходное средство для восстановления и против выпадения волос. Придает им естественный объем. Регулируют работу сальных желез и нормализует гидролипидный баланс кожи головы, поэтому отлично подходит для жирных волос. Можно использовать абсолютно для всех типов волос - сухих, жирных, нормальных. Аргановое масло в составе обеспечивает защиту кожу головы, предупреждая развитие кожных заболеваний. Подходит для кудрявых и вьющихся волос, делает ваши локоны блестящими, мягкими и гладкими. Это универсальный шампунь для взрослых, а также мальчиков и девочек - подростков. Если вы мечтаете о длинных волосах, но не можете отрастить их, потому что сталкиваетесь с проблемой секущихся кончиков, рекомендуем вам этот шампунь. Аргановое масло способствует регенерации тонких поврежденных волос, проникая в их пористую структуру, и запечатывает поврежденные кончики, обеспечивая придание объема. Отлично подойдет для блондинок, чтобы надолго сохранить оттенок осветленных волос ярким и насыщенным. Идеальная находка для непослушных волос, которые часто путаются, чтобы облегчить их расчесывание. Этот глубоко очищающий шампунь можно использовать для волос светлых и темных оттенков, в том числе и для обесцвеченных и седых. Очень экономичный расход, одного флакона вам хватит надолго. Bio Clinic Argan Ultra Care - уходовая косметика премиум - класса на основе натуральных питательных ингредиентов. Не содержит sls и других вредных компонентов. При регулярном применении шампуня вы забудете о ломкости волос, они приобретут идеальную гладкость и блеск, станут здоровыми и крепкими. В преддверии новогодних праздников все хотят выглядеть потрясающе. Bio Clinic Argan Ultra Care- и полезный подарок на нг для любимой мамы, вашей девушки, сестры, или подруги. Вы можете собрать подарочный набор, добавив в комплект к шампуню другую продукцию для ухода за волосами, например маску или бальзам - ополаскиватель. Подарите своим волосам любовь и заботу вместе с Bio Clinic Argan Ultra Care. У нас есть акции и распродажи, вы можете купить наши товары в подарок со скидкой! \n\n\n\nРазвернуть описание\n\n  Описания пока нет. Возможно, оно появится тут позже   Состав  \n\n         Дополнительная информация Срок годности 4 года Высота упаковки 27 см Прямые поставки от производителя Прямые поставки от производителя Вес товара без упаковки (г) 690 г Тип волос для всех типов волос; для окрашенных волос; для поврежденных волос Любимые герои Нет Форма упаковки без давления Объем товара 600 мл Ширина упаковки 12 см Упаковка Бутылка Назначение косметического средства для волос; мужская линия; для ванн и душа Страна производства Турция Раздел меню профессиональная косметика; органическая косметика; аптечная косметика Длина упаковки 9 см Действие увлажнение; очищение; питание Вес товара с упаковкой (г) 830 г Комплектация бутылка; упаковка  \n\n\n\n\n\nРазвернуть характеристики\n\n    У товара пока нет характеристик. Возможно, они появятся тут позже    Качество подтверждено   Качество подтверждено            Вся информация основывается на последних сведениях от производителя         Сообщить о неточности    ", "category_name": "Аптечная косметика"}