{"name": "Blackberry Love Blackberry Love Возбудитель для женщин капли 10 мл 18+ лучшая виагра", "rating": 5, "review_count": 512, "article": 140667400, "order_count": 1400, "price": 720, "old_price": 4500, "detail": "  О товаре      Описание    ТЕГИ: Товары для взрослых для женщин и мужчин смазка для средство интимная 18+ эротическая дамиана капли крем игрушки масло женский возбудитель возбуждение таблетки сильный препараты потенции мужская виагра интим плюс эрекции самый эффективный сильнейший рандеву распутница рендез войс rendex vous мощный реальный лиса серебряная аптека лучший алкоголем действует запах вкус fox silver порно спрей травы power лекарство золотая популярные  китайские аналог организм аптечный мазь супер usa анонимно экстра здоровье половой акт натуральные белоруссия любовь мире резинка оргазм феромон напиток растворимый япония россия леди растительный сила набор ампул вода жене подруге кролик бюджетный анальный жидкость сакура ночь флаконе леса либидо sex японский вумен secret студентке порошковый надежный германия минет качество сразу анал палец трусики porno здоровье оригинал косметика съедобная климакс клиторный презерватив вещество беременных школьнице легальное поперс медленно быстрого месячных жесткий бдсм ОПИСАНИЕ:Возбудитель для женщин в каплях без запаха и цвета товары для взрослых увеличивают влечение к мужчине, усиливают чувствительность. Афродизиак для секса близости повышает либидо улучшает самочувствие при климаксе помогает в достижении оргазма повышают чувствительность сексуальность красота половое влечение стимулирует работу влагалища.Женьшень повышает чувствительность эрогенных зон и снимает напряжение, а дягиль расслабляет и помогает вырабатывать естественную смазку. Бады для здоровья женщин мужчин средство имеет преимущества перед кремами маслами смазками гель таблетки лубрикант эротическое белье интимная съедобная косметика игры и сувениры возбуждающий напиток продукты добавки пищевые. Дамиана восстанавливает половую активность. Отличный подарок 18+ любимому на праздник 8 марта 14 февраля 23 день рождения влюбленных святого валентина девушке жене. В составе этого средства находятся компоненты способствующие сильному возбуждению и усилению полового влечения потенции. \n\n\n\nРазвернуть описание\n\n  Описания пока нет. Возможно, оно появится тут позже   Состав  анис 10%, женьшень 10%, перуанская мака 10%, дягиль 10%, афродизиак 40%, дамиана 10%, L- аргинин 10%\n\n         Дополнительная информация Высота упаковки 10 см Длина упаковки 5 см Ширина упаковки 5 см Упаковка анонимная упаковка; пузырек с дозатором Коллекция все сезоны Срок годности 1095 суток Страна производства Россия Тип косметики съедобная косметика; возбуждающее средство; товары для взрослых интим виагра 18+ совместим с алкоголем сильное лучшее Форма упаковки без давления; флакон с крышкой; стимулятор для женщин точки g оргазма возбудитель в каплях Объем средства 10 мл Объем товара 10 мл Комплектация Анонимная упаковка; коробочка; пузырек 10 мл с дозатором Сезон круглогодичный  Другие функции Хрупкость хрупкое; надежно упаковано; капли для возбуждения  \n\n\n\n\n\nРазвернуть характеристики\n\n    У товара пока нет характеристик. Возможно, они появятся тут позже    Качество подтверждено   Качество подтверждено            Вся информация основывается на последних сведениях от производителя         Сообщить о неточности    ", "category_name": "Интимная косметика"}