{"name": "Edshop Edshop Гигиенические прокладки с крылышками 260мм 20шт/10шт ежедн", "rating": 5, "review_count": 1, "article": 150489054, "order_count": 5, "price": 294, "old_price": 600, "detail": "  О товаре      Описание    Женские гигиенические ночные прокладки для умеренных выделений. Подойдут в роддом так и послужат как послеродовые. Улучшенная защита и новый стильный дизайн помогут в личной гигиене. Обеспечивают комфорт и уверенность до 100%* Прокладка стала более гибкой, чтобы лучше подстраиваться под анатомию твоего тела и защищать от протеканий. ЛУЧШЕ ПРИЛЕГАЕТ до 0% ПРОТЕКАНИЙ. Мягкие крылышки, надежно крепятся к белью и не натирают кожу -Эстетичная форма прокладки и нежный женственный дизайн добавят удовольствия при использовании в менструальные дни. В комплектацию входят ежедневные гигиенические прокладки которые подарят ощущение свежести, но и помогают всем девушкам чувствовать себя красивыми! Эти Ежедневные Гигиенические прокладки позволяют коже дышать, обеспечивая свежесть и комфорт до 12 часов. Тонкие и гибкие Ежедневные Гигиенические прокладки, повторяющие каждое ваше движение- Клейкая прослойка от края до края фиксирует прокладку на вашем белье в течение всего дня- Дышащие Ежедневные Гигиенические прокладки- 4 гибкие зоны для трусиков любой формы \n\n\n\nРазвернуть описание\n\n  Описания пока нет. Возможно, оно появится тут позже   Состав  целлюлоза, материал нетканый\n\n         Дополнительная информация Назначение прокладок для критических дней; ежедневные; ночные Длина упаковки 21 см Высота упаковки 8 см Раздел меню для ванны и душа; красота; Средство личной гигиены Страна производства Армения Прямые поставки от производителя да Упаковка полимерная пленка; Защитная коробка Вес товара с упаковкой (г) 200 г Ширина упаковки 11 см Комплектация Прокладки гигиенические 15шт. - 1 уп; Прокладки ежедневные 5шт.  Общие характеристики Количество предметов в упаковке 10 шт.  \n\n\n\n\n\nРазвернуть характеристики\n\n    У товара пока нет характеристик. Возможно, они появятся тут позже    Качество подтверждено   Качество подтверждено            Вся информация основывается на последних сведениях от производителя         Сообщить о неточности    ", "category_name": "Средства личной гигиены"}