{"name": "ETTA High Tech ETTA High Tech Наушники беспроводные Air 2 для iPhone и Android", "rating": 5, "review_count": 4732, "article": 138834549, "order_count": 32400, "price": 1050, "old_price": 5835, "detail": "  О товаре      Описание    ЖИВИ С МУЗЫКОЙ!!! Новые наушники Air 2 последнего поколения от ETTA High Tech полностью изменят Ваше представление об использовании беспроводных наушников.  ПОДАРОК: Стильный чехол из премиального силикона! Технология пространственного аудио окружает звуком со всех сторон. Ощущения просто волшебные!!! Достаньте наушники из футляра — и они уже готовы к работе и мгновенно подключаются к вашим устройствам iPhone (IOS) или на Android. Благодаря совместной работе оптических сенсоров и акселерометра — наушники понимают, когда Вы их надеваете. Они также способны распознавать положение: воспроизведение автоматически приостанавливается, когда Вы их снимаете. Сенсорное управление позволит Вам всегда оставаться на связи! Можете использовать и один, и два наушника, а при прослушивании музыки или подкастов начинать воспроизведение или переходить к следующему треку двойным касанием наушника. Новый датчик нажатия поддерживает ещё больше возможностей управления: включайте и останавливайте воспроизведение, перематывайте треки, отвечайте на звонки и завершайте их. В этих Air 2 используется новый чип, и в зависимости от того, используете Вы один или два наушника, чип автоматически распределяет аудио и включает микрофон соответствующим образом. Используйте функции «Привет, Siri» «Привет, Google», чтобы изменить громкость, включить другую песню, позвонить или даже проложить маршрут. В беспроводных наушниках установлен обновлённый Bluetooth 5.0, который позволяет отдаляться от телефона на 10-20 метров без потери качества звука и приема вызова. В Air 2 можно до 5 часов слушать музыку и до 3 часов разговаривать по телефону без подзарядки. Кроме того, зарядный кейс обеспечивает наушникам несколько циклов зарядки, благодаря чему они могут работать более 30 часов. Нужна быстрая подзарядка? Всего 15 минут зарядки в футляре позволяют ещё до 3 часов слушать музыку или до 2 часов разговаривать по телефону. Как сами Air 2, так и зарядный кейс MagSafe устойчивы к воздействию пота и воды и имеют рейтинг IPX4, поэтому Вы сможете использовать наушники под дождём и во время интенсивных тренировок .- Быстрая подзарядка в футляре .- Футляр заряжается через разъём Lightning .- Беспроводная зарядка наушников .- Высокое качество звучания музыки и голоса .- Целый день телефонных разговоров и прослушивания музыки благодаря футляру, который обеспечивает наушникам несколько циклов зарядки. Если Вы искали Air Pods оригинал, проводные наушники или игровые  наушники, попробуйте Air 2 от ETTA High Tech! Вы будете в восторге!!! БЕСПРОВОДНЫЕ НАУШНИКИ ПРИХОДЯТ В НАШЕЙ  БРЕНДИРОВАННОЙ КОРОБОЧКЕ! Имеют презентабельный вид и будут прекрасным подарком на День Всех Влюблённых, 23 февраля, 8 марта, коллеге в офис, День Рождения, а также отличным презентом в качестве знака внимания! ПРИЯТНОЙ ПОКУПКИ!!! С уважением и наилучшими пожеланиями, команда ETTA ht! \n\n\n\nРазвернуть описание\n\n  Описания пока нет. Возможно, оно появится тут позже   Состав  \n\n         Общие характеристики Тип подключения Беспроводное автоматическое подключение; bluetooth блютуз; оригинальная анимация Степень пылевлагозащиты IPX4 Вид наушников Беспроводные сенсорные блютуз наушники; беспроводные вкладыши с кейсом для зарядки; портативная внутриканальная гарнитура с микрофоном Гарантийный срок дополнительная гарантия от магазина (гарантийный талон в комплекте); есть \"клиент сервис\" для покупателей; 1 год Модель детские блютуз наушники; гарнитура с микрофоном Bluetooth; AirPods 2 беспроводные наушники для Айфон и Андройд  Технические особенности Минимальная воспроизводимая частота 20 Гц Максимальная воспроизводимая частота 20000 Гц Диаметр мембраны 10 мм Радиус беспроводной связи 15 метров Импеданс 32 Ом Чувствительность 96 дБ  Дополнительная информация Страна производства Гонконг Длина упаковки 11 см Материал корпуса abs-пластик Тип акустического оформления закрытые; открытые; полуоткрытые Тип крепления наушников вкладыши; внутриканальные; в ушной раковине Совместимость android; Windows; honor; Samsung; huawei xiaomi; Со всеми Bluetooth устройствами; hoco i12 f9 i100 A2 M10 K55; Беспроводное подключение к телефону и компьютеру; Apple; iOS iPhone Длина кабеля (м) 1 Возрастная группа для детей Высота предмета 3 см Глубина предмета 10 см Высота упаковки 6 см Ширина предмета 3 см Назначение товара наушники для смартфона android iphone apple; прослушивания музыки и просмотров фильмов; для общения разговоров игр занятий спортом Доп. опции наушников Беспроводные наушники Bluetooth; беспроводные наушники гарнитура с микрофоном; TWS для андроида и айфона Тип соединения Беспроводные наушники; беспроводная блютуз гарнитура с микрофоном; не проводные TWS Ширина упаковки 12 см Вес товара с упаковкой (г) 210 г Вес товара без упаковки (г) 150 г Комплектация Кейс для зарядки наушников - 1шт; Кабель для зарядки кейса - 1шт; оригинальная коробка - 1шт. подарочная упаковка 1шт.; чехол в подарок и гарантийный талон; Беспроводные наушники для Айфон и Андроид  Питание Емкость аккумулятора 350 мАч для зарядного чехла; 30 мАч для наушников Время зарядки Кейс - 50 минут; Наушники - 15 минут Время работы от аккумулятора до 5 часов от одной зарядки от кейса; кейс заряжает наушники 3 - 4 раза; 30 ч  Интерфейсы и разъемы Разъем подключения наушников Lightning (зарядка кейса)  Другие функции Хрупкость не хрупкое; готовый подарок; Надежно упакован  Связь Беспроводные интерфейсы Беспроводные наушники Bluetooth 5.0; гарнитура Bluetooth Android Apple; не с ушками игровые; GPS; блютуз  \n\n\n\n\n\nРазвернуть характеристики\n\n    У товара пока нет характеристик. Возможно, они появятся тут позже    Качество подтверждено   Качество подтверждено            Вся информация основывается на последних сведениях от производителя         Сообщить о неточности    ", "category_name": "Детская электроника"}