{"name": "FS Sport FS Sport Спортивный костюм на молнии", "rating": 5, "review_count": 1334, "article": 18819325, "order_count": 6300, "price": 8687, "old_price": 11900, "detail": "  О товаре      Описание    Мужской спортивный костюм премиального качества. Произведен в Турции. В комплект костюма входят: спортивная ветровка на молнии без капюшона с воротником-стойкой и спортивный брюки (штаны) прямые (классические). В изделии использованы лучшие материалы (хлопок, плащевка). Ткань футер 2 нитка без начеса, мягкая и приятная на ощупь, не скатывается и не теряет форму, прекрасно гладится. Хлопковый трикотажный костюм удобен как для спорта (бег, фитнес, тренировки, велоспорт, спортивная ходьба), так и для повседневной носки. Костюм мужской спортивный классический, комфортного кроя. Подходит для высоких, невысоких и среднего роста. Свободный спортивный костюм идеален для тренировок, отдыха, прогулок, фитнеса и бега. Спортивный костюм лучше всего подойдет на осень (осенний) и на сезон весна (весенний), также можно взять его на прохладное лето (летний) и теплую зиму.Наши костюмы представлены в цветах: синий серый красный темно-синий светло-синий оливковый белый хаки черный. Одежда бренда FS sport отлинчый подарок мужу мужчине папе брату другу сыну внуку дедушке! Также это отлиный подарок на день рождения, новый год и 23 февраля. \n\n\n\nРазвернуть описание\n\n  Описания пока нет. Возможно, оно появится тут позже   Состав  хлопок, эластан, полиэстер\n\n         Дополнительная информация Тип карманов прорезные на молнии Температурный режим от +5 до +25 Фактура материала Мягкая гладкая поверхность Рост модели на фото 187 см Рисунок нет Тип ростовки для высоких Декоративные элементы вышивка ТНВЭД 6103109000 Спортивное назначение бег; спортивная ходьба; туризм Тип рукава длинные Модель костюма брючный Утеплитель без утепления Модель брюк костюма прямые Покрой свободный Коллекция Весна-Лето 2021 Страна производства Турция Уход за вещами Стирка при 30 °С Особенности модели дышащий материал Вид застежки молния; на молнии Длина упаковки 5 см Высота упаковки 35 см Ширина упаковки 30 см Комплектация Ветровка - 1шт.; Штаны спортивные - 1 шт Пол Мужской Сезон круглогодичный; демисезон  \n\n\n\n\n\nРазвернуть характеристики\n\n    У товара пока нет характеристик. Возможно, они появятся тут позже    Качество подтверждено   Качество подтверждено            Вся информация основывается на последних сведениях от производителя         Сообщить о неточности    ", "category_name": "Костюмы"}