{"name": "Gouter Gouter Куртка косуха кожаная женская", "rating": 5, "review_count": 8028, "article": 144680877, "order_count": 2500, "price": 3949, "old_price": 10970, "detail": "  О товаре      Описание    Куртка женская осенняя полуприлегающего силуэта - неотъемлемая часть любого гардероба. ВНИМАНИЕ! Размерная сетка в ленте фотографий. Куртка маломерит. Укороченная модель куртки кожаной классической имеет стеганую фактуру, два кармана и застежку молнию. Эко-кожа обладает способность пропускать воздух, водонепроницаема, гипоаллергенна, приятна на ощупь. Куртка из эко-кожи обеспечит тепло и удобство в прохладную погоду. Это базовая модель позволит Вам создавать неповторимые и модные образы. Сочетание с джинсами, футболкой и кедами - это беспроигрышный вариант наряда в стиле casual. А также интересно смотрится сочетание кожаной куртки с женственными вещами - платьями, длинными юбками, блузками. Обувь может быть любой: от классических вечерних туфель до сапог в ковбойском стиле и ботинок. Понравится тем, кому необходимы: куртка демисезонная кожаная, весенняя, летняя, куртка кожаная для девочки подростка, куртка женская больших размеров, автоледи, бомбер, косуха, осенняя, кожанка, черная, короткая \n\n\n\nРазвернуть описание\n\n  Описания пока нет. Возможно, оно появится тут позже   Состав  \n\n         Дополнительная информация Параметры модели на фото (ОГ-ОТ-ОБ) 87-62-87 Утеплитель без утеплителя Фактура материала кожаный Рост модели на фото 174 см ТНВЭД 6102209000 Назначение офис; для беременных; большие размеры Страна производства Россия Тип карманов прорезные Температурный режим +5 °C до +15°C Рисунок однотонная черная Опции капюшона косуха женская без капюшона больших размеров Тип ростовки для высоких Вид застежки молния Любимые герои кожанка женская осенняя Размер на модели M Материал подкладки искусственный материал Особенности модели Демисезонная осенняя весенняя Покрой приталенный Спортивное назначение велоспорт; мотоспорт; страйкбол Коллекция Весна-Лето 2022 Опции опушки бомбер без опушки Уход за вещами сухая чистка Длина упаковки 80 см Высота упаковки 1 см Ширина упаковки 60 см Комплектация Куртка кожаная эко кожа - 1 шт; ТЭГИ куртка женская экокожа весенняя демисезонная кожаная косуха демисезон для девочки; ТЭГИ верхняя одежда женская для беременных куртка авиатор бомбер спортивная; ТЭГИ пуховик одежда для спорта зимняя детская ветровка для подростков искусственная кожа Пол Женский Сезон демисезон  \n\n\n\n\n\nРазвернуть характеристики\n\n    У товара пока нет характеристик. Возможно, они появятся тут позже    Качество подтверждено   Качество подтверждено            Вся информация основывается на последних сведениях от производителя         Сообщить о неточности    ", "category_name": "Мотоспорт"}