{"name": "Gremlin Gremlin Палатка детская игровая домик шатер 3 в 1 игрушки подарок", "rating": 5, "review_count": 425, "article": 58452308, "order_count": 2500, "price": 2664, "old_price": 9517, "detail": "  О товаре      Описание    Детский игровой домик палатка надолго станет любимой игрушкой ваших детей. Универсальная яркая расцветка подходит как для девочек, так и для мальчиков. Развивающий игровой комплекс  состоит из трех частей - палатка, которую можно использовать отдельно, тоннель лабиринт и сухой бассейн с сеткой и баскетбольным кольцом. Манеж можно наполнить шариками или постелить детский коврик. Шары для сухого бассейна в комплект не входят. Набор с оригинальным дизайном привлечет внимание малышей как в 10 - 11 месяцев, так и детей в 5 - 6 лет. Он позволит маленькому ребенку придумать новые игры: воображать, что это замок, шалаш, шатер, пляжная палатка или вигвам для игр. Игровой домик отлично подходит для игр в помещении и на улице, поскольку имеет плотное вшитое дно. Виг вам для малышей легко раскладывается и компактно складывается в удобную сумку чехол на молнии. Игровой комплекс удобно переносить и брать с собой в поездку на природу, на дачу, на море или на пляж. Палатка для детей изготовлена из безопасной плотной водонепроницаемой ткани, вставки из сетки пропускают воздух и защищают от солнца и насекомых. Палатка большая и просторная. Ткань легко очистить с помощью влажной тряпки. У вашего ребенка появится свой любимый уголок, где можно весело играть с друзьями, отдыхать, читать или спать.  Игровая палатка Гремлин – это лучший подарок для детей любого возраста. Быстросборная конструкция с каркасом, обшитым мягкой тканью идеальна для организации игровой зоны в детской комнате сыночка и дочки. В сложенном виде комплекс имеет небольшой размер, не займет много места, вызовет большой восторг, чем развивашки и другие игрушки. Красивое изделие с рисунком рыб и обитателей водного мира, шаров и звезд - лучший подарок для крестника на крестины. У нас есть акции и распродажи, вы можете купить наши товары в подарок со скидкой. \n\n\n\nРазвернуть описание\n\n  Описания пока нет. Возможно, оно появится тут позже   Состав  \n\n         Дополнительная информация Возрастные ограничения 3+; Без ограничений; 0+ Ширина предмета 300 см Высота предмета 135 см Глубина предмета 105 см Особенности игровой палатки быстрая сборка; безопасные материалы; Просторная Страна производства Китай Любимые герои Замок Дисней Ширина упаковки 50 см Высота упаковки 4 см Назначение подарка для ребенка; девочке; мальчику Длина упаковки 50 см Место применения для дачи; для дома; для улицы, пикника, отдыха на природе Повод день рождения; 23 февраля; 8 марта Вес с упаковкой (кг) 1.17 кг Комплектация Сумка - 1 шт; Тунель - 1 шт; Детский игровой домик- 1 шт; бассейн сухой 1 шт  Технические особенности Материал изделия полиэстер; ткань; металл  \n\n\n\n\n\nРазвернуть характеристики\n\n    У товара пока нет характеристик. Возможно, они появятся тут позже    Качество подтверждено   Качество подтверждено            Вся информация основывается на последних сведениях от производителя         Сообщить о неточности    ", "category_name": "Игровые комплексы"}