{"name": "Hodel Smart Hodel Smart Детское гибкое радужное пианино", "rating": 5, "review_count": 84, "article": 91748764, "order_count": 700, "price": 3516, "old_price": 10990, "detail": "  О товаре      Описание    Сертифицированное пианино детское от шведского бренда Hodel Smart! Идеальное детское пианино, чтобы познакомить вашего ребенка с миром музыки и через игру на музыкальном инструменте развивать слух, память и детскую моторику пальцев! Гибкое пианино детское Hodel Smart - развивающая игрушка с 49 клавишами, 128 тонами, 14 демо - песнями, имеет разъем для наушников, выход для микрофона, функцию записи, изготовлена из натурального и безопасного силикона с мягкой водонепроницаемой поверхностью, которую легко чистить! Покупая пианино детское музыкальное от Hodel Smart, вы получаете возможность воспроизводить звуки и играть на 128 музыкальных инструментах на выбор! Управлять игрой на детском пианино с микрофоном очень просто благодаря специальной панели управления, в которой легко разобраться, настроить нужный инструмент, громкость, добавить ритм, записать свою игру! Кроме того, комплектация каждого пианино для малышей уникальна и не имеет аналогов: Включена Нотная Книга с 23 детскими песнями и Инструкция на русском языке – Учитесь и Играйте по Нотам, Включена Подставка Для Нот с авторским дизайном для удобной игры на музыкальном пианино, Включены Наушники – высокое качество звука и никакого шума для окружающих, Включены USB кабель + Адаптер – пианино можно подключить в любом удобном месте! Само радужное пианино гибкое и легко сворачивается в рулон, поэтому его удобно хранить и легко взять с собой! Не упустите отличный подарок музыкальное пианино детское от Hodel Smart! Гарантия 1 год!\n\n\nДетское пианино – это отличный подарок для девочки 4 года и мальчика 3 года. Оно поможет ребенку познакомиться с музыкой и развить слух. Это электронное пианино – цифровое пианино, которое позволит малышу играть на нем мелодии с легкостью.\n\nДетский синтезатор – это идеальная игрушка для девочек, которые любят музыку! Он создан для обучения, и при этом может выполнять роль прекрасного подарка на 4 года девочке. Пианино – это классический музыкальный инструмент, и это пианино для обучения поможет девочке быстро научиться играть на фортепиано.\n\nДетское пианино цифровое для девочки – это музыкальный центр, в котором есть все, что необходимо для музыкального обучения. Чтобы овладеть игрой на пианино, необходимо потратить много времени на обучение. Но с помощью этой игрушки, ребенок быстро научится играть на пианино. Она подходит малышам, которые увлекаются музыкой и мечтают о том, чтобы научиться играть на цифровом пианино.\n\nМузыкальные инструменты игрушечные очень популярны среди детей всех возрастов. Пионино – это один из самых любимых музыкальных инструментов. Детское пианино – это игрушка для девочки 4 года, которая поможет ребенку развить музыкальный слух и овладеть навыками игры.\n\nИгрушки для девочек 4 года могут быть разными, но электронное пианино – цифровое пианино – будет лучшим выбором. Оно подходит как для детей, которые только начинают осваивать музыку, так и для тех, кто уже умеет играть на фортепиано. Подарок для девочки 4 года – это синтезатор, который обязательно понравится ей! \n\n\n\nРазвернуть описание\n\n  Описания пока нет. Возможно, оно появится тут позже   Состав  \n\n         Дополнительная информация Страна производства Китай Возрастные ограничения 5+ Эффекты звуки; музыкальное сопровождение; теплые эмоции Вес товара с упаковкой (г) 1318 г Ширина упаковки 24 см Материал игрушки силикон Высота упаковки 10 см Любимые герои обучение ребенка Количество батареек для работы 4 шт. Тип элемента питания батарейка Длина упаковки 24 см Вид музыкального инструмента пианино  Питание Типоразмер элемента питания AAA  \n\n\n\n\n\nРазвернуть характеристики\n\n    У товара пока нет характеристик. Возможно, они появятся тут позже    Качество подтверждено   Качество подтверждено            Вся информация основывается на последних сведениях от производителя         Сообщить о неточности    ", "category_name": "Музыкальные"}