{"name": "Loft mood Loft mood Опора мебельная ножки  подстолье лофт", "rating": 5, "review_count": 73, "article": 99846274, "order_count": 1100, "price": 4000, "old_price": 10000, "detail": "  О товаре      Описание    Комплект опоры .Стильное и прочное металлическое подстолье для стола Лофт, выполненное в черном  Муар 9005 цвете, подойдет для самостоятельного создания мебели вашего интерьер кухни ,балкона и так же гостинной . Опора мебельная Лофт  регулируемая, имеет пластиковые элементы для ножки, которые позволяют установить стол на неровной поверхности и регулировать высоту изделия до 3-х см для сглаживания неровностей пола, а так же они не царапают пол. Подстолье металлическое изготовления, Опора мебельная черная изготавливается при помощи порошкового окрашивания, которое обеспечит надежную защиту влаги и коррозии, позволит избежать следов царапин при частом воздействии на поверхность. Кроме того конструкция стальная может быть использована не только для создания мебели Лофт, но и для реставрации уже имеющего стола на случай если Вашу опору следует заменить или нужно изменить габариты стола. Благодаря мощной раме металлическое подстолье легко выдерживает нагрузку до 200 кг.Ваш дом станет уютнее благодаря новому поколению! \n\n\n\nРазвернуть описание\n\n  Описания пока нет. Возможно, оно появится тут позже   Состав  \n\n         Дополнительная информация Страна производства Россия Ширина предмета 54 см Вес с упаковкой (кг) 4 кг Глубина предмета 30 см Высота предмета 73 см Длина упаковки 75 см Высота упаковки 20 см Ширина упаковки 56 см Комплектация Опора мебельная 1 или 2 шт в зависимости от комплектации.  Материалы Материал изделия металл  Общие характеристики Количество предметов в упаковке 1  \n\n\n\n\n\nРазвернуть характеристики\n\n    У товара пока нет характеристик. Возможно, они появятся тут позже    Качество подтверждено   Качество подтверждено            Вся информация основывается на последних сведениях от производителя         Сообщить о неточности    ", "category_name": "Мебельная фурнитура"}