{"name": "LOVANIMAL LOVANIMAL Миска для животных кошек и собак тройная", "rating": 5, "review_count": 3174, "article": 82119020, "order_count": 9500, "price": 714, "old_price": 1035, "detail": "  О товаре      Описание    ТРИ ДОПОЛНИТЕЛЬНЫХ МИСКИ В ПОДАРОК! Тройная миска для кошек, котят и собак мелких пород, обеспечивает правильное положение тела питомца при приема воды и пищи. Данный наклон миски для собак и кошек позволит предотвратить проблемы с пищеварением, вздутием живота и снимает нагрузку с позвоночника. Каждую из трёх чаш можно вынуть и при необходимости помыть. Подставка и сами миски для кошек и собак изготовлены из высококачественного пищевого пластика. Тройная миска для собак и кошек является достаточно прочной. В комплекте к миске для животных двойной идут прорезиненные накладки, благодаря которым подставка не будет скользить по полу. Вы можете отрегулировать высоту подставки по мере роста вашего питомца: примените максимальную силу и разогните подставку до нужного уровня, она точно не сломается. Поилка для кормления кошек и собак мелких пород, подойдут и для грызунов (кролика, хорька, енота, морских свинок и других). В комплекте: Подставка, Прозрачная миска - 3 шт., Белая миска 3 шт., Накладки 4 шт. Полезный объем каждой пластиковой миски - 270 мл. Размеры подставки - 40x13x6,5 см, размеры миски - 14x13x8 см. Миски можно мыть в посудомоечной машине. Нельзя использовать для очень горячей пищи и подогревать в микроволновой печи. \n\n\n\nРазвернуть описание\n\n  Описания пока нет. Возможно, оно появится тут позже   Состав  пищевой пластик 100%\n\n         Материалы Материал изделия пищевая пластмасса  Дополнительная информация Особенности товара для животных Миска для кошек и собак мелких пород; тройная миска с подставкой; Миска для дома и улицы Вес товара с упаковкой (г) 994 г Вид грызуна хорек; шиншилла; кролик Вид животного для собак; для кошек; для грызунов Вид миски для животных пластиковая миска; миска для воды и корма; тройная миска на подставке Вместимость миски 270 мл Высота предмета 14 см Страна производства Россия Упаковка картонная коробка Ширина предмета 40 см Длина упаковки 37 см Высота упаковки 12 см Ширина упаковки 28 см Комплектация подставка; миска прозрачная 3 шт; миска белая 3 шт  \n\n\n\n\n\nРазвернуть характеристики\n\n    У товара пока нет характеристик. Возможно, они появятся тут позже    Качество подтверждено   Качество подтверждено            Вся информация основывается на последних сведениях от производителя         Сообщить о неточности    ", "category_name": "Аксессуары для кормления"}