{"name": "Nika Nika Доска для рисования напольная магнитная складная с азбукой", "rating": 5, "review_count": 1314, "article": 132500976, "order_count": 3100, "price": 1966, "old_price": 3026, "detail": "  О товаре      Описание    Мольберт детский двухсторонний НИКА растущий  (мелки, азбука ) Nika. Две рабочие поверхности: меловая - доска для рисования мелом; магнитная - доска для рисования маркером на водной основе и крепления магнитов. Доска для рисования детская регулируется по высоте от 73,5 до 107,5 см, что позволяет заниматься творчеством и обучением детям разного возраста. В комплекте большой пенал для хранения мелков и маркеров, зажим для крепления бумажных листов, цветные счеты.  Маркеров в наборе нет. Мольберт напольный легко складывается и компактно хранится. Пластиковые заглушки на опорах. Устойчивая конструкция. Габаритные размеры (ДхШхВ) 755х516х70 мм. Размер рабочей поверхности 53х46 см. Для детей до 7 лет. Доска для творчества - отличный подарок ребенку, дочери, сыну, который прекрасно подойдет для рисования, изучения азбуки и счёта. Подойдет для подарка мальчику и девочке. \n\n\n\nРазвернуть описание\n\n  Описания пока нет. Возможно, оно появится тут позже   Состав  \n\n         Дополнительная информация Высота предмета 108 см Вид доски для рисования магнитная; для маркера; для мела Состав набора пенал для хранения-1шт; зажим для крепления бумажных листов-1шт; доска для рисования - 1 шт Ширина предмета 51 см Назначение для ребенка; для мальчика; для девочки Вес товара без упаковки (г) 6900 г Страна производства Россия Возрастные ограничения 3+; 3 + Длина упаковки 77 см Высота упаковки 7 см Ширина упаковки 55 см Комплектация мольберт детский двусторонний-1шт; пенал для хранения мелков и маркеров-1шт; зажим для крепления бумажных листов-1шт  Материалы Материал изделия металл; пластик  \n\n\n\n\n\nРазвернуть характеристики\n\n    У товара пока нет характеристик. Возможно, они появятся тут позже    Качество подтверждено   Качество подтверждено            Вся информация основывается на последних сведениях от производителя         Сообщить о неточности    ", "category_name": "Развивающие игрушки"}