{"name": "Rabby Rabby Ультратонкие презервативы. Набор 15 штук", "rating": 5, "review_count": 173, "article": 90850450, "order_count": 1200, "price": 325, "old_price": 813, "detail": "  О товаре      Описание    Защита, комфорт и премиальное качество – это все про классические презервативы Rabby! Уникальная технология производства с использованием гипоаллергенных протеинов шелка и витаминов В создает дополнительную антибактериальную защиту. Обильная силиконовая смазка и гладкий прочный латекс обеспечивают максимальную чувствительность без риска для надежности. Он абсолютно гипоаллергенный и подойдет для любых видов секса, в том числе и для оральных ласк. Оптимальные параметры презервативов гарантирует комфорт для любых параметров. Большая упаковка позволяет устроить эротическое свидание 18+ со взрослыми играми не на одну ночь! Презервативы не обладают ароматом и не имеют в составе цветных материалов. Наш интим магазин предлагает широкий выбор товаров для взрослых, как для женщин, так и для мужчин. Попробуй вибратор кролик для одновременной стимуляции клитора и точки G, а насадка на член подойдет парням, который хотел бы увеличить свой размер. А специально для пар у нас есть интим бдсм наборы для самых жарких игр. А если ты хочешь предстать перед своим партнером в сексуальном образе, можешь заказать белье от размера s до xxl size. Перед использованием добавь лубрикант на водной основе (продаются отдельно), чтобы сделать ощущения еще более приятными. В комплект включены также пакетики для утилизации. Все товары рэбби доставляются абсолютно анонимно в непрозрачном пакете без наименований и маркировок. Испытай настоящую страсть вместе с Rabby! \n\n\n\nРазвернуть описание\n\n  Описания пока нет. Возможно, оно появится тут позже   Состав  \n\n         Дополнительная информация Срок годности 5 лет Материал презерватива латекс Особенности презерватива ультратонкие; классические; со смазкой Упаковка анонимная непрозрачная упаковка; Плотный пакет Страна производства Китай Вес товара с упаковкой (г) 60 г Длина упаковки 6 см Высота упаковки 12 см Ширина упаковки 5 см Комплектация Презервативы - 15 шт  Общие характеристики Количество предметов в упаковке 15 шт  \n\n\n\n\n\nРазвернуть характеристики\n\n    У товара пока нет характеристик. Возможно, они появятся тут позже    Качество подтверждено   Качество подтверждено            Вся информация основывается на последних сведениях от производителя         Сообщить о неточности    ", "category_name": "Контрацептивы и лубриканты"}