{"name": "wepl wepl Жилет утепленный с капюшоном, стеганый (безрукавка)", "rating": 5, "review_count": 417, "article": 14484035, "order_count": 700, "price": 5147, "old_price": 12554, "detail": "  О товаре      Описание    ПОЖАЛУЙСТА, ЧТОБЫ ТОЧНО ПОДОБРАТЬ РАЗМЕР, ВЫБИРАЙТЕ ЕГО ПО ТАБЛИЦЕ РАЗМЕРОВ  НА ФОТО. Произведите замеры на себе и сверьтесь с Таблицей размеров.  Стеганый мужской жилет цвета хаки, с капюшоном, подойдет для повседневной носки, занятий спортом, фитнеса, бега, рыбалки, охоты, в качестве рабочей одежды, водителю за рулем, для комфортного отдыха на даче. Зимний жилет с высоким воротником защищен ветро- и влагозащитной мембранной тканью LOKKER POINT с сопротивлением порывам ветра и влаги 3К. Гидрофобный утеплитель Isosoft (плотность 140 гр.) - материал нового поколения, представляющий собой сверхтонкие волокна, закрепленные между двумя слоями очень тонкой ткани. ИННОВАЦИОННЫЙ УТЕПЛИТЕЛЬ В 4 РАЗА ТОНЬШЕ СИНТЕПОНА И В 2 РАЗА ТЕПЛЕЕ! Он полностью сохраняет свои свойства после многочисленных стирок из-за особой структуры покрытия и конструкции волокон. Имеет двухстороннюю полимерную обработку, исключающую миграцию волокон. Благодаря особенностям структуры способен обеспечивать выход наружу влаги и обеспечивает комфортную терморегуляцию в любую погоду. В результате, при эксплуатации наших жилетов, не создается эффект сауны и человек не испытывает дискомфорт. Объемный капюшон, который можно регулировать, размер фиксируется стопперами. Воротник изнутри отделан плотным и теплым флисом (300 гр.). Имеется внутренний боковой карман на молнии. Глубокие боковые карманы, внутри флис, мягкий и теплый. Классическая модель безрукавки позволяет надевать ее на свитер, с тренировочным или туристическим, беговым или трикотажным костюмом. Жилет подойдет на невысоких и на средний рост, на полных и худых. Главное, при определении размера, произвести замеры на себе и свериться с Таблицей размеров на фото-слайде. Модель жилета не оверсайз (oversize), поэтому очень важно правильно выбрать размер. Безрукавка идет на средний рост 170-185 см. Длина изделия по спинке - 74 см., допустима погрешность в 1-2 см. Легкая тужурка составит удобный комплект к рубашке и футболке с длинным рукавом. Утепленный дутый жилет на осень и весну заменит пуховую куртку, подойдет взрослому и подростку, военному и на работу, в поход и на пикник. Не военная (армейская, милитари), но смотрится как тактическая. Универсальная демисезонная жилетка - классика гардероба современного мужчины. Удивите своего любимого, закажите спортивный жилет в подарок на день рождения, Новый год, праздник, 23 февраля, просто без повода по акции со скидкой, и дополните осенний, весенний, зимний образ стильным базовым жилетом. Широкий размерный ряд представлен в больших и маленьких размерах ( от 46 до 68). Жилетки представлены в широком цветовом диапазоне: черный, серый, синий, хаки. Успейте купить душегрейку пока идет распродажа. Не куртка. Обратите внимание на спортивные костюмы, бейсболки и футболки от нашего бренда. Цвет изделия может отличаться от представленного на фото в зависимости от освещения и индивидуальных настроек/характеристик вашего экрана. \n\n\n\nРазвернуть описание\n\n  Описания пока нет. Возможно, оно появится тут позже   Состав  полиэстер\n\n         Дополнительная информация Рисунок однотонная Покрой прямой Тип ростовки для высоких Материал подкладки полиэстер Вид застежки молния ТНВЭД 6211339000 Назначение большие размеры; офис; повседневная Декоративные элементы без декоративных элементов,однотонная Особенности модели мембранная ткань Размер на модели 48 (M) Уход за вещами бережная стирка при 30 градусах Рост модели на фото 185 см Коллекция Весна-Лето 2023 Опции капюшона несъемный капюшон Модель жилета утепленный с капюшоном Любимые герои Утепленный жилет с капюшоном Тип карманов прорезные, имеется внутренний карман на молнии Страна производства Россия Фактура материала гладкая фактура Длина упаковки 40 см Высота упаковки 9 см Ширина упаковки 30 см Комплектация жилет - 1 шт Пол Мужской  \n\n\n\n\n\nРазвернуть характеристики\n\n    У товара пока нет характеристик. Возможно, они появятся тут позже    Качество подтверждено   Качество подтверждено            Вся информация основывается на последних сведениях от производителя         Сообщить о неточности    ", "category_name": "Пиджаки, жилеты и жакеты"}