{"name": "АКВАЛОР АКВАЛОР Беби  для носа с рождения", "rating": 4, "review_count": 15, "article": 75631932, "order_count": 400, "price": 656, "old_price": 772, "detail": "  О товаре      Описание    Аквалор Беби - изотонический стерильный раствор для ежедневной гигиены, увлажнения слизистой носа и лечения насморка у детей с первых дней жизни и взрослых. Преднзначен для орошения и промывания полости носа для детей и взрослых. Аквалор беби 150 мл представляет собой аэрозоль в металлическом баллоне с анатомической насадкой для носа и пластиковым колпачком. Содержимое баллона прозрачная бесцветная жидкость без запаха, со слабосоленым вкусом, являющаяся стерильным раствором морской воды, с изотонической концентрацией соль NaCl. Оказывает благоприятное воздействие на слизистую оболочку полости носа и носоглотки, способствует уменьшению заложенности носа и восстановлению носового дыхания. Насадка Аквалор беби снабжена ограничительным кольцом, исключающим глубокое проникновение и травматизацию слизистой полости носа ребенка. Тип распыления - мягкий душ. Профилактика и комплексное лечение острых и хронических воспалительных заболеваний полости носа, околоносовых пазух и носоглотки. \n\n\n\nРазвернуть описание\n\n  Описания пока нет. Возможно, оно появится тут позже   Состав  вода очищенная, вода морская\n\n         Дополнительная информация Упаковка Картонная коробка + защитная пупырчатая пленка Путь введения назально Вес товара с упаковкой (г) 220 г Возрастные ограничения Нет ограничений; 0 + Действие препарата профилактика ЛОР заболеваний; при насморке; промывание носа Объем (мл) 150 мл Порядок отпуска без рецепта Страна производства Франция Срок годности 3 года Длина упаковки 5 см Высота упаковки 40 см Ширина упаковки 21 см Комплектация 1 упаковка – спрей 150 мл  Общие характеристики Количество предметов в упаковке 1  \n\n\n\n\n\nРазвернуть характеристики\n\n    У товара пока нет характеристик. Возможно, они появятся тут позже    Качество подтверждено   Качество подтверждено            Вся информация основывается на последних сведениях от производителя         Сообщить о неточности    ", "category_name": "Ухо, горло, нос"}