{"name": "Книга по психологии саморазвития Книга по психологии саморазвития Мышление предпринимателя | Сагдеев Станислав | Книга подарок", "rating": 5, "review_count": 1, "article": 158247265, "order_count": 5, "price": 2975, "old_price": 3500, "detail": "  О товаре      Описание    Новинка. Увлекательная книга о предпринимательстве в России. Мышление предпринимателя автор Сагдеев Станислав.\n\nИстория о том, как строят бизнес в России. Молодой бедный папа студент после прочтения бестселлера Думай и богатей Наполеона Хилла изменил мышление, стал использовать аффирмации и превратился в богатого папу миллионера. Кто-то подумает что это выдумка, мистика, магия, эзотерика. Возможно и так, ведь у автора даже есть отсылки на астрологию и нумерологию когда он себе искал нишу для бизнеса. Но если вы только задумываетесь о создании бизнеса или вы в поиске ниши, прочитайте эту книгу, возможно также и вы узнаете секреты и найдете для себя полезные рекомендации по созданию бизнеса и о том как справляться с тяжелыми ситуациями.\n\nАвтор убедился на собственном опыте, что подсознание играет огромную роль в достижении результатов, а также в том что мысли материальны! Чтобы повысить эффективность прочтения, лучше сразу делать записи в блокнот выписывая простые правила постановки целей или в специальные поля подготовленные в конце книги. Для повышения самооценки, дополнительно себе можете завести дневник благодарностей, где будете отмечать маленькие победы на пути к большим целям.\n\nНекоторые читатели сравнивают этот роман с классикой и мировым бестселлером Атлант расправил плечи автора Айн Рэнд, ведь основные события также разворачиваются вокруг железных дорог. Только они не выдуманы и не где-то там далеко. Описываемые в книжке события проходят в Нижнеудинске, Ангарске, Иркутске, Москве, Лондоне, Ташкенте и Чарваке.\n\nЭто подарочная качественная и приятная на ощупь книга, с твердой обложкой. Белоснежные страницы, крупный шрифт, современный дизайн и даже есть закладка. Все продумано до мелочей. Эта книга отлично подойдет для подарка мужчине, женщине, девушке, подростку и даже ребенку. Большинству читателей нравится, что это не занудная книга о маркетинге, менеджменте, инвесторе или финансах и не скучная автобиография. Это больше художественная книга или бизнес роман с элементами детектива и эзотерики. Вы можете сделать прекрасный подарок подруге на день рождения или просто так, без повода, человеку который который находится в тяжелой жизненной ситуации. Автор на собственном примере показывает как попадал и выходил из тяжелейших кризисов используя силу позитивного мышления и подсознания. Когда вокруг все рушится и уходит из-под ног, единственное на что можно реально опереться, находится не где-то далеко, а внутри себя.\n\nТемы затронутые в книге: # философия, психология, поиск себя, мотивация, ответственность, размышления о жизни, эмоциональный интеллект, денежное мышление, успех, самооценка, любовь, самообразование, осознанность, саморазвитие, эффективность, позитивное мышление, стратегические цели, бизнес с нуля, масштабирование, инвестиции, тендеры.\n\nВ книге есть практические задания и упражнения. Чаще задавайте себе вопросы как коуч. Чем больше будете думать над задачей, тем легче станет находить нужные ответы. Иногда лучшие ответы приходят во сне. Будьте открытыми.\n\nПриятного чтения. Пусть у вас все получится! Верьте, чудеса случаются!\n\n\n \n\n\n\nРазвернуть описание\n\n  Описания пока нет. Возможно, оно появится тут позже   Состав  \n\n         Дополнительная информация Повод без повода; день рождения; для себя Количество страниц 328 шт. Страна производства Россия Жанры/тематика Бизнес и менеджмент; Саморазвитие для взрослых; Психология Глубина предмета 5 см Вес товара с упаковкой (г) 700 г Обложка твердая; тиснение Цикл подарок подруге; книги для подростков; подарок на день рождения Автор Сагдеев Станислав Серия бизнес идеи; бизнес с нуля; книги романы Назначение подарка любимому; коллеге - для него; подруге Год выпуска 2022; 2023 Ширина предмета 16 см Языки русский Возрастные ограничения 12+ Вид бумаги офсетная; типографская; книжки Высота предмета 5 см Редакция Writer's Way Иллюстратор книги по психологии ISBN 978‐5‐907485‐35‐8 Наименование книги Мышление предпринимателя Длина упаковки 27 см Высота упаковки 5 см Ширина упаковки 16 см Комплектация Книга - 1 шт  \n\n\n\n\n\nРазвернуть характеристики\n\n    У товара пока нет характеристик. Возможно, они появятся тут позже    Качество подтверждено   Качество подтверждено            Вся информация основывается на последних сведениях от производителя         Сообщить о неточности    ", "category_name": "Бизнес и менеджмент"}