{"name": "Малевичъ Малевичъ Карандаши набор 8шт, карандаши простые для рисования в кейсе", "rating": 5, "review_count": 4385, "article": 9262630, "order_count": 88100, "price": 236, "old_price": 381, "detail": "  О товаре      Описание    Художественные чернографитные карандаши Малевич Graf'Art предназначены для рисования и отвечают всем требованиям предъявляемым к профессиональной художественной продукции. Высококачественный грифель очищен от примесей за счет чего штриховка получается равномерной и четкой. Диаметр грифеля отличается в зависимости от степени мягкости карандаша. Высококачественная древесина обеспечивает легкое затачивание, корпус и грифель не крошится и остаются целыми даже при падении карандаша. В наборе простые карандаши 8 степеней мягкости: 2Н, Н, НВ, В, 2В, 4В, 6В, 8В. \nКарандаши находятся в красивой подарочной металлической коробке, которая надежно защищает их от повреждений и может использоваться как пенал.\n \n\n\n\nРазвернуть описание\n\n  Описания пока нет. Возможно, оно появится тут позже   Состав  \n\n         Дополнительная информация Количество цветов (шт.) 8 Диаметр грифеля 3 мм Вид упаковки металлический короб Страна производства Китай Вес товара с упаковкой (г) 115 г Длина стержня 170 мм Форма карандаша шестигранная Назначение школа Твердость карандаша Н; В; НВ Тип карандашей чернографитные; простые; шестигранные Особенности карандашей в металлическом кейсе; заточенные; долговечные Длина упаковки 2 см Высота упаковки 19 см Ширина упаковки 8 см Комплектация Карандаш - 8 шт; простой карандаш; чернографитный карандаш  Общие характеристики Количество предметов в упаковке 8 шт  \n\n\n\n\n\nРазвернуть характеристики\n\n    У товара пока нет характеристик. Возможно, они появятся тут позже    Качество подтверждено   Качество подтверждено            Вся информация основывается на последних сведениях от производителя         Сообщить о неточности    ", "category_name": "Чертежные принадлежности"}