{"name": "Сульсен Сульсен Шампунь для волос от перхоти женский и мужской Sulsen 250 мл", "rating": 5, "review_count": 4448, "article": 22936370, "order_count": 100000, "price": 341, "old_price": 696, "detail": "  О товаре      Описание    Причинами возникновения перхоти могут быть: неправильный уход за волосами, пересушивание кожи головы, недостаток витаминов А и группы В, нервное перенапряжение, нарушение желудочно-кишечного тракта, психоэмоциональные стрессовые ситуации, заболевания эндокринной системы, а также грибковые заболевания.\nПроблемы начинаются, когда мертвых клеток эпидермиса становится слишком много. Основные причины этого — усиление работы сальных желез и избыточное размножение микроскопического грибка Pityrosporum Ovale. Этот дрожжевой грибок всегда живет на коже человека, но от стресса, из-за нарушений иммунитета и обмена веществ, при некоторых заболеваниях или неправильном уходе за волосами его количество увеличивается.\n\nКак справиться с перхотью.\n\nОдно из средств, способствующих снижению количества перхоти, — это сульсен, натуральное соединение двух элементов: селена и серы. Он улучшает состояние при разных видах перхоти: жирной, жидкой, сухой, так как может:\n●    нормализовать работу сальных желез;\n●    затормозить рост грибковой микрофлоры;\n●    замедлить рост клеток эпидермиса;\n●    снять шелушение и зуд кожи.\n\nСера, входящая в состав сульсена, дополнительно укрепляет волосы, придает им блеск.\nКомпоненты Сульсена обогащены кондиционирующими добавками и экстрактами растений, восстанавливающими структуру волос и укрепляющими их корни.\nСульсен Forte с кетоконазолом - женский и мужской шампунь против перхоти, зуда и себореи для всех типов волос. Шампунь мужской от перхоти лечебный Мирролла Sulsen Forte с кетоконазолом обладает зарекомендовавшей себя эффективностью. Способствует устранению видимой перхоти, обеспечивает восстанавливающий, питательный, увлажняющий, противосеборейный эффект. Активный состав шампуня, в который входят Selenium Sulfide и Ketoconazole, снижает интенсивность проявлений перхоти, способствует уменьшению раздражения и шелушения кожи головы, регуляции работы сальных желез. Оказывает восстанавливающее действие на барьерные функции кожи головы. Корректирует признаки повышенной жирности кожи головы, уменьшает зуд и шелушение. Шампунь от перхоти с кетоконазолом Sulsen обладает высокой антимикотической активностью и способен угнетать рост грибов. Содержащийся в составе шампуня кетоконазол оказывает антимикробное действие. Сульфид селена в составе шампуня - эффективный противогрибковый компонент. Салициловая кислота мягко отшелушивает ороговевшие клетки кожи головы. Экстракт чистотела улучшает структуру волос, помогает лечению перхоти, снимает зуд и воспаления, избавляет от себореи. Экстракт чистотела оказывает благотворное лечебное воздействие на ослабленные волосы: предотвращает выпадение и придает им здоровый блеск. Экстракт корня репейника способствует быстрому восстановлению структуры волос и кожного покрова головы. Мягкая моющая формула деликатно очищает волосы без эффекта пересушивания. Специальный состав нейтральных компонентов шампуня обеспечивает мягкую очистку. Шампунь Sulsen Forte кетоконазолом подходит для нормальных и жирных волос, предназначен для борьбы с перхотью у женщин, мужчин и подростков от 14 лет. Подходит для очищения и ухода за женской и мужской кожей головы, склонной к себорее и перхоти. Идеален как шампунь мужской от перхоти для раздраженной кожи и шампунь для волос женский профессиональный. Сульсеновый шампунь с кетоконазолом отлично подходит для женщин и мужчин в качестве средства от перхоти по уходу за волосами всех типов. Наши средства от перхоти Sulsen подойдут как прекрасный подарок мужчине на 23 февраля и на 8 Марта женщине. Красивая картонная коробка послужит в качестве подарочной упаковки шампуня для подарка  на день рождения, Новый год и по любому поводу. СПОСОБ ПРИМЕНЕНИЯ. Намочить волосы. Нанести небольшое количество шампуня и распределить по всей длине волос. Вспенить шампунь и массировать в течение 2-3 минут. Смыть большим количеством воды. При попадании в глаза немедленно промойте водой. Использовать через день в течение 4-6 недель, после чего перейти на регулярное применение шампуня Mirrolla Sulsen Mite еще в течение 1,5-2 месяцев. Повторять курс по необходимости. Для усиления эффекта рекомендуется применять вместе с пастой Mirrolla Sulsena Forte с кетоконазолом. \n \n\n\n\nРазвернуть описание\n\n  Описания пока нет. Возможно, оно появится тут позже   Состав  сульфид селена (сульсен), вода, Лауретсульфат натрия, кокамидопропил бетаин, лаурил глюкозид, глицерин, экстракт корня репейника, экстракт чистотела, экстракт корня солодки, поликватерниум-7, силикон кватерниум-16 (и) ундецет-11 (и) бутилоктанол (и) ундецет-5, кетоконазол, аллантоин ацетил метионин, лаурет-2, карбомер нейтрализованный, эдта, метилхлоризотиазолинон, метилизотиазолинон, лимонная кислота, отдушка\n\n\n\nРазвернуть состав\n\n         Дополнительная информация Прямые поставки от производителя да Назначение косметического средства Подарки мужчинам; подарки женщинам; уход за волосами Ставка НДС 20 Действие уход за волосами; для мам; для роста волос Объем товара 250 мл Форма упаковки без давления Раздел меню Шампуни и кондиционеры; Инструменты для парикмахеров; аптечная косметика Страна производства Россия Вес товара с упаковкой (г) 282 г Вес товара без упаковки (г) 240 г Тип волос для всех типов волос; для жирных волос; для нормальных волос Срок годности 36 месяцев Упаковка флакон; картонная коробка Длина упаковки 5 см Высота упаковки 18 см Ширина упаковки 8 см Комплектация профессиональная косметика; органическая косметика; мужская линия; мужской уход; для ванн и душа  \n\n\n\n\n\nРазвернуть характеристики\n\n    У товара пока нет характеристик. Возможно, они появятся тут позже    Качество подтверждено   Качество подтверждено            Вся информация основывается на последних сведениях от производителя         Сообщить о неточности    ", "category_name": "Аптечная косметика"}